baguette_bi/__init__.py
baguette_bi/actions.py
baguette_bi/alembic/alembic.ini
baguette_bi/alembic/migrations/env.py
baguette_bi/alembic/migrations/script.py.mako
baguette_bi/alembic/migrations/versions/.gitignore
baguette_bi/alembic/migrations/versions/eba70920adc0_init.py
baguette_bi/bi.py
baguette_bi/cache/__init__.py
baguette_bi/cache/base.py
baguette_bi/cache/null.py
baguette_bi/cache/redis.py
baguette_bi/cli/__init__.py
baguette_bi/core/__init__.py
baguette_bi/core/chart.py
baguette_bi/core/connections/__init__.py
baguette_bi/core/connections/base.py
baguette_bi/core/connections/sql_alchemy.py
baguette_bi/core/connections/vega_datasets.py
baguette_bi/core/context.py
baguette_bi/core/data_request.py
baguette_bi/core/dataset.py
baguette_bi/examples/__init__.py
baguette_bi/examples/altair_examples/case_studies/__init__.py
baguette_bi/examples/altair_examples/case_studies/airport_connections.py
baguette_bi/examples/altair_examples/case_studies/barley_trellis_plot.py
baguette_bi/examples/altair_examples/case_studies/natural_disasters.py
baguette_bi/examples/altair_examples/case_studies/one_dot_per_zipcode.py
baguette_bi/examples/altair_examples/case_studies/seattle_weather_heatmap.py
baguette_bi/examples/altair_examples/case_studies/us_population_facet.py
baguette_bi/examples/altair_examples/case_studies/wheat_and_wages.py
baguette_bi/examples/altair_examples/connections.py
baguette_bi/examples/altair_examples/datasets.py
baguette_bi/examples/altair_examples/folders.py
baguette_bi/examples/altair_examples/init__.py
baguette_bi/examples/altair_examples/other/__init__.py
baguette_bi/examples/altair_examples/other/binned_heatmap.py
baguette_bi/examples/altair_examples/other/marginal_histograms.py
baguette_bi/examples/altair_examples/other/normalized_parallel_coordinates.py
baguette_bi/examples/altair_examples/other/ridgeline_plot.py
baguette_bi/examples/altair_examples/other/text_over_heatmap.py
baguette_bi/examples/altair_examples/other/violin_plot.py
baguette_bi-0.1.11.dist-info/entry_points.txt
baguette_bi-0.1.11.dist-info/WHEEL
baguette_bi-0.1.11.dist-info/METADATA
baguette_bi-0.1.11.dist-info/RECORD
