Metadata-Version: 2.1
Name: baguette-bi
Version: 0.1.11
Summary: 
Author: Mikhail Akimov
Author-email: rovinj.akimov@gmail.com
Requires-Python: >=3.9,<4.0
Classifier: Programming Language :: Python :: 3
Classifier: Programming Language :: Python :: 3.9
Requires-Dist: Babel (>=2.9.1,<3.0.0)
Requires-Dist: Jinja2 (>=3.0.1,<4.0.0)
Requires-Dist: Markdown (>=3.3.4,<4.0.0)
Requires-Dist: Pygments (>=2.9.0,<3.0.0)
Requires-Dist: SQLAlchemy (>=1.4.15,<2.0.0)
Requires-Dist: WTForms (>=2.3.3,<3.0.0)
Requires-Dist: aiofiles (>=0.7.0,<0.8.0)
Requires-Dist: alembic (>=1.6.5,<2.0.0)
Requires-Dist: altair (>=4.1.0,<5.0.0)
Requires-Dist: fastapi (>=0.65.1,<0.66.0)
Requires-Dist: gunicorn (>=20.1.0,<21.0.0)
Requires-Dist: httptools (>=0.2.0,<0.3.0)
Requires-Dist: itsdangerous (>=2.0.1,<3.0.0)
Requires-Dist: passlib[bcrypt] (>=1.7.4,<2.0.0)
Requires-Dist: psycopg2-binary (>=2.8.6,<3.0.0)
Requires-Dist: python-dotenv (>=0.17.1,<0.18.0)
Requires-Dist: python-multipart (>=0.0.5,<0.0.6)
Requires-Dist: redis (>=3.5.3,<4.0.0)
Requires-Dist: typer (>=0.4.0,<0.5.0)
Requires-Dist: uvicorn (>=0.17.4,<0.18.0)
Requires-Dist: uvloop (>=0.15.2,<0.16.0)
Requires-Dist: vega-datasets (>=0.9.0,<0.10.0)
